MANIFEST.in
README
setup.py
docs/Makefile
docs/build/.gitignore
docs/source/common.rst
docs/source/conf.py
docs/source/index.rst
docs/source/yaclub.rst
docs/source/yacollections.rst
docs/source/yaentry.rst
docs/source/yaperson.rst
docs/source/yaresource.rst
docs/source/_static/logo.png
pyyaru/__init__.py
pyyaru/pyyaru.py
pyyaru/tests.py
pyyaru.egg-info/PKG-INFO
pyyaru.egg-info/SOURCES.txt
pyyaru.egg-info/dependency_links.txt
pyyaru.egg-info/not-zip-safe
pyyaru.egg-info/requires.txt
pyyaru.egg-info/top_level.txt