Metadata-Version: 1.0
Name: pyyaru
Version: 0.3.2
Summary: Python interface for ya.ru blog service API.
Home-page: http://github.com/idlesign/pyyaru
Author: Igor 'idle sign' Starikov
Author-email: idlesign@yandex.ru
License: UNKNOWN
Platform: UNKNOWN
Classifier: Development Status :: 3 - Alpha
Classifier: Environment :: Web Environment
Classifier: Intended Audience :: Developers
Classifier: Operating System :: OS Independent
Classifier: Programming Language :: Python
